[
  {
    "unique_id": "card001",
    "name": "Sample Strike",
    "description": "Deal 3 damage.",
    "type_text": "Attack Action",
    "cost": "1",
    "pitch": 1,
    "power": "3",
    "defense": "2",
    "played_horizontally": false,
    "is_token": false,
    "is_starter": false,
    "blitz_legal": true,
    "cc_legal": true,
    "commoner_legal": true,
    "ll_legal": false,
    "types": ["Action"],
    "subtypes": ["Attack"],
    "keywords": ["Go Again"],
    "functional_keywords": ["Breakthrough"],
    "printing": {
      "set": "Welcome to Rathe",
      "edition": "1st",
      "foiling": "R",
      "rarity": "Rare",
      "image_url": "https://example.com/card001.jpg",
      "tcgplayer_url": "https://tcgplayer.com/card001",
      "artists": ["John Doe"],
      "card_number": "001"
    }
  }
]
